LICENSE.txt
MANIFEST.in
README.md
setup.py
opengb/__init__.py
opengb/config.py
opengb/database.py
opengb/server.py
opengb/utils.py
opengb.egg-info/PKG-INFO
opengb.egg-info/SOURCES.txt
opengb.egg-info/dependency_links.txt
opengb.egg-info/entry_points.txt
opengb.egg-info/requires.txt
opengb.egg-info/top_level.txt
opengb/etc/opengb.conf
opengb/etc/init.d/opengb
opengb/frontend/classic/index.html
opengb/frontend/classic/fonts/glyphicons-halflings-regular.svg
opengb/frontend/classic/scripts/bootstrap.min.js
opengb/frontend/classic/scripts/jquery-1.11.3.min.js
opengb/frontend/classic/scripts/opengb_gui.js
opengb/frontend/classic/styles/bootstrap-theme.min.css
opengb/frontend/classic/styles/bootstrap.min.css
opengb/frontend/classic/styles/opengb.gui.css
opengb/frontend/opengb/index.html
opengb/frontend/opengb/static/app.22137b510b00147fb8ed96664dbd6787.css
opengb/frontend/opengb/static/app.2a748243a9bb1308a235.js
opengb/frontend/opengb/static/foundation-icons.svg
opengb/printer/__init__.py
opengb/printer/base.py
opengb/printer/dummy.py
opengb/printer/marlin.py
opengb/tests/__init__.py
opengb/tests/test_server.py
opengb/tests/test_utils.py