Metadata-Version: 1.1
Name: opengb
Version: 0.19.0
Summary: OpenGB printer control.
Home-page: http://www.re3d.org/
Author: re:3D
Author-email: support@re3D.org
License: LICENSE.txt
Platform: UNKNOWN
Classifier: Development Status :: 4 - Beta
Classifier: Intended Audience :: End Users/Desktop
Classifier: License :: OSI Approved :: GNU Affero General Public License v3
Classifier: Operating System :: POSIX :: Linux
Classifier: Programming Language :: Python
Classifier: Programming Language :: Python :: 3
Classifier: Programming Language :: Python :: 3.4
